arabic_phonemizer/__init__.py
arabic_phonemizer/constants.py
arabic_phonemizer/phonemizer.py
arabic_phonemizer-0.0.3.dist-info/LICENCE.txt
arabic_phonemizer-0.0.3.dist-info/METADATA
arabic_phonemizer-0.0.3.dist-info/WHEEL
arabic_phonemizer-0.0.3.dist-info/top_level.txt
arabic_phonemizer-0.0.3.dist-info/RECORD
