Metadata-Version: 2.2
Name: arabic_phonemizer
Version: 0.0.3
Summary: A simple and efficient Arabic phonemizer.
Author-email: Muhammad Abd Al-sattar <muhammadabdalsattar@gmail.com>
Requires-Python: >=3.8
License-File: LICENCE.txt
